timestring/__init__.py
timestring/test_init.py
timestringpy-1.2.1.dist-info/licenses/LICENSE
timestringpy-1.2.1.dist-info/METADATA
timestringpy-1.2.1.dist-info/WHEEL
timestringpy-1.2.1.dist-info/top_level.txt
timestringpy-1.2.1.dist-info/RECORD
