Metadata-Version: 2.4
Name: TimestringPy
Version: 1.2.1
Summary: Parse a timestring into a floating number.
Home-page: https://github.com/The-LukeZ/TimestringPy
Author: The-LukeZ
Maintainer: The-LukeZ
License: MIT
Classifier: Programming Language :: Python :: 3
Classifier: License :: OSI Approved :: MIT License
Classifier: Operating System :: OS Independent
Requires-Python: >=3.10
License-File: LICENSE
Dynamic: author
Dynamic: classifier
Dynamic: description
Dynamic: description-content-type
Dynamic: home-page
Dynamic: license
Dynamic: license-file
Dynamic: maintainer
Dynamic: requires-python
Dynamic: summary
